simple_pygame_gui/Button.py
simple_pygame_gui/FloatBox.py
simple_pygame_gui/FreeSans.ttf
simple_pygame_gui/FreeSansBold.ttf
simple_pygame_gui/Switch.py
simple_pygame_gui/Switch_off.png
simple_pygame_gui/Switch_on.png
simple_pygame_gui/TextBox.py
simple_pygame_gui/__init__.py
simple_pygame_gui-0.0.6.dist-info/LICENSE
simple_pygame_gui-0.0.6.dist-info/METADATA
simple_pygame_gui-0.0.6.dist-info/WHEEL
simple_pygame_gui-0.0.6.dist-info/top_level.txt
simple_pygame_gui-0.0.6.dist-info/RECORD
