Metadata-Version: 2.1
Name: simple_pygame_gui
Version: 0.0.6
Summary: Usefull GUI elements for your pygame projects
Home-page: https://github.com/KVN1701/pygame_gui
Author: Kevin Ell
Author-email: kevinell74@gmail.com
Classifier: Programming Language :: Python :: 3
Classifier: License :: OSI Approved :: MIT License
Classifier: Operating System :: OS Independent
Requires-Python: >=3.10
License-File: LICENSE
Requires-Dist: pygame
